ghostlog/__init__.py
ghostlog-0.3.0.dist-info/METADATA
ghostlog-0.3.0.dist-info/RECORD
ghostlog-0.3.0.dist-info/WHEEL
ghostlog-0.3.0.dist-info/top_level.txt
