Metadata-Version: 2.1
Name: ghostlog
Version: 0.3.0
Summary: Easily log to syslog or stdout.
Home-page: https://bitbucket.org/spctr/spectro-ghostlog
Author: Ezequiel Pochiero
Author-email: ezequiel@spect.ro
License: UNKNOWN
Download-URL: https://bitbucket.org/spctr/spectro-ghostlog/get/v0.3.0.zip
Keywords: log,logging,syslog
Platform: UNKNOWN
Classifier: Development Status :: 4 - Beta
Classifier: Intended Audience :: Developers
Classifier: Programming Language :: Python :: 3
Classifier: Topic :: Utilities
Classifier: Topic :: Software Development :: Libraries :: Python Modules
Classifier: Topic :: System :: Logging
Classifier: Topic :: System :: Systems Administration
